flask_scrypt.py
setup.cfg
setup.py
Flask_Scrypt.egg-info/PKG-INFO
Flask_Scrypt.egg-info/SOURCES.txt
Flask_Scrypt.egg-info/dependency_links.txt
Flask_Scrypt.egg-info/not-zip-safe
Flask_Scrypt.egg-info/requires.txt
Flask_Scrypt.egg-info/top_level.txt