Metadata-Version: 1.1
Name: Flask-Scrypt
Version: 0.1.1
Summary: Flask-Scrypt extension provides scrypt password hashing                and random salt generation for Flask.
Home-page: http://github.com/grobins2/flask-scrypt
Author: Gilbert Robinson
Author-email: grobins2@gmail.com
License: MIT
Platform: any
Classifier: Development Status :: 4 - Beta
Classifier: Environment :: Web Environment
Classifier: Intended Audience :: Developers
Classifier: License :: OSI Approved :: MIT License
Classifier: Operating System :: OS Independent
Classifier: Programming Language :: Python
Classifier: Topic :: Internet :: WWW/HTTP :: Dynamic Content
Classifier: Topic :: Software Development :: Libraries :: Python Modules
